simanim/__init__.py
simanim/__pycache__/__init__.cpython-37.pyc
simanim/__pycache__/__init__.cpython-38.pyc
simanim/abstract/__init__.py
simanim/abstract/api_functions.py
simanim/abstract/api_primitives.py
simanim/abstract/core.py
simanim/abstract/__pycache__/__init__.cpython-37.pyc
simanim/abstract/__pycache__/__init__.cpython-38.pyc
simanim/abstract/__pycache__/api_functions.cpython-37.pyc
simanim/abstract/__pycache__/api_functions.cpython-38.pyc
simanim/abstract/__pycache__/api_primitives.cpython-37.pyc
simanim/abstract/__pycache__/api_primitives.cpython-38.pyc
simanim/abstract/__pycache__/core.cpython-37.pyc
simanim/abstract/__pycache__/core.cpython-38.pyc
simanim/pyodide/__init__.py
simanim/pyodide/driver.py
simanim/pyodide/gui.py
simanim/pyodide/__pycache__/__init__.cpython-38.pyc
simanim/pyodide/__pycache__/driver.cpython-38.pyc
simanim/pyodide/__pycache__/gui.cpython-38.pyc
simanim/qt/__init__.py
simanim/qt/driver.py
simanim/qt/gui.py
simanim/qt/__pycache__/__init__.cpython-37.pyc
simanim/qt/__pycache__/__init__.cpython-38.pyc
simanim/qt/__pycache__/driver.cpython-37.pyc
simanim/qt/__pycache__/driver.cpython-38.pyc
simanim/qt/__pycache__/gui.cpython-37.pyc
simanim/qt/__pycache__/gui.cpython-38.pyc
simanim-0.0.4.dist-info/METADATA
simanim-0.0.4.dist-info/WHEEL
simanim-0.0.4.dist-info/top_level.txt
simanim-0.0.4.dist-info/RECORD
