Metadata-Version: 2.1
Name: simanim
Version: 0.0.4
Summary: Python framework for simple simulations
Home-page: https://github.com/Petlja/simanim
Author: Fondacija Petlja
Author-email: team@petlja.org
License: UNKNOWN
Platform: UNKNOWN
Classifier: Programming Language :: Python :: 3.6
Classifier: License :: OSI Approved :: MIT License
Classifier: Operating System :: OS Independent
Requires-Python: >=3.6
Requires-Dist: pyside2
